{
  "self": {
    "version": "1.0.0",
    "name": "org.cognita.ml.utilities.Classifier",
    "description": "Classifies the output of Predictor",
    "component_type": "docker"
  },
  "streams": {},
  "services": {
    "calls": [
      {
        "config_key": "cognita-db",
        "request": {
          "format": "org.cognita.ml.request.AlarmGenerator",
          "version": "1.0.0"
        },
        "response": {
          "format": "org.cognita.ml.response.AlarmGenerator",
          "version": "1.0.0"
        }
      }
    ],
    "provides": [
      {
        "route": "/classifier",
        "request": {
          "format": "org.cognita.ml.request.Classifier",
          "version": "1.0.0"
        },
        "response": {
          "format": "org.cognita.ml.response.Classifier",
          "version": "1.0.0"
        }
      }
    ]
  },
  "parameters": [],
  "auxilary": {},
  "artifacts": [
    {
      "uri": "fake.nexus.att.com/dcae/kpi_anomaly:1.0.0",
      "type": "docker image"
    }
  ]
}